src/__init__.py
src/models.py
src/utils.py
passgen_py-0.1.1.dist-info/METADATA
passgen_py-0.1.1.dist-info/WHEEL
passgen_py-0.1.1.dist-info/entry_points.txt
passgen_py-0.1.1.dist-info/top_level.txt
passgen_py-0.1.1.dist-info/RECORD
